dj_notif/__init__.py
dj_notif/apps.py
dj_notif/consumers.py
dj_notif/managers.py
dj_notif/models.py
dj_notif/routes.py
dj_notif/serializers.py
dj_notif/urls.py
dj_notif/views.py
dj_notif/base/__init__.py
dj_notif/base/consumers.py
dj_notif/base/managers.py
dj_notif/base/models.py
dj_notif/base/serializers.py
dj_notif/utils/__init__.py
dj_notif/utils/async_funcs.py
dj_notif/utils/main.py
dj_notif-0.2.2.dist-info/licenses/LICENSE
dj_notif-0.2.2.dist-info/METADATA
dj_notif-0.2.2.dist-info/WHEEL
dj_notif-0.2.2.dist-info/top_level.txt
dj_notif-0.2.2.dist-info/RECORD
