Metadata-Version: 2.4
Name: dj_notif
Version: 0.2.2
Summary: A comprehensive Django package for managing notifications with automatic dispatching, WebSocket-based real-time delivery, and category-based organization
Author-email: Armin Fekri <armiin.fekri1@gmail.com>
Maintainer-email: Armin Fekri <armiin.fekri1@gmail.com>
License: MIT License
Project-URL: Homepage, https://github.com/Hexoder/DjangoNotification
Project-URL: Documentation, https://github.com/Hexoder/DjangoNotification#readme
Project-URL: Repository, https://github.com/Hexoder/DjangoNotification
Project-URL: Issues, https://github.com/Hexoder/DjangoNotification/issues
Project-URL: Changelog, https://github.com/Hexoder/DjangoNotification/blob/main/CHANGELOG.md
Keywords: django,notifications,websocket,real-time,channels,jwt,broadcast,rest-api
Classifier: Development Status :: 4 - Beta
Classifier: Intended Audience :: Developers
Classifier: License :: OSI Approved :: MIT License
Classifier: Operating System :: OS Independent
Classifier: Programming Language :: Python :: 3
Classifier: Programming Language :: Python :: 3.10
Classifier: Programming Language :: Python :: 3.11
Classifier: Programming Language :: Python :: 3.12
Classifier: Framework :: Django
Classifier: Framework :: Django :: 5.2
Classifier: Topic :: Internet :: WWW/HTTP
Classifier: Topic :: Internet :: WWW/HTTP :: Dynamic Content
Classifier: Topic :: Communications
Classifier: Topic :: Software Development :: Libraries :: Python Modules
Requires-Python: >=3.10
License-File: LICENSE
Requires-Dist: django>=5.2
Requires-Dist: djangorestframework>=3.15.2
Requires-Dist: channels>=4.2.0
Requires-Dist: django-channels-jwt>=0.0.3
Requires-Dist: channels-redis>=4.1.0
Provides-Extra: dev
Requires-Dist: pytest>=7.0.0; extra == "dev"
Requires-Dist: pytest-django>=4.5.0; extra == "dev"
Requires-Dist: black>=22.0.0; extra == "dev"
Requires-Dist: flake8>=5.0.0; extra == "dev"
Requires-Dist: mypy>=1.0.0; extra == "dev"
Provides-Extra: docs
Requires-Dist: sphinx>=5.0.0; extra == "docs"
Requires-Dist: sphinx-rtd-theme>=1.0.0; extra == "docs"
Dynamic: license-file
